cachetools_redis/__init__.py
cachetools_redis/rediscache.py
cachetools_redis/redislru.py
cachetools_redis/redisttl.py
cachetools_redis-0.1.2.dist-info/LICENSE
cachetools_redis-0.1.2.dist-info/WHEEL
cachetools_redis-0.1.2.dist-info/METADATA
cachetools_redis-0.1.2.dist-info/RECORD
